Workbook

Sheet Raw Data
A1: BRAND | B1: PesaPal Kenya | D1: PERIOD | E1: 1 Jan 2025 – 31 Mar 2025 (90 days) | G1: ANALYST | H1: TECKLER NDIANY
A2: Date | B2: Week | C2: Platform | D2: Content Type | E2: Post Topic | F2: Reach | G2: Impressions | H2: Likes | I2: Comments | J2: Shares | K2: Saves | L2: Profile Visits | M2: Link Clicks | N2: New Followers | O2: Engagement Rate (%) | P2: Notes
A3: 01-Jan-2025 | B3: W01 | C3: Instagram | D3: Promotional | E3: Refer a friend get KSh 100 | F3: 921 | G3: 1060 | H3: 10 | I3: 2 | J3: 0 | K3: 0 | L3: 53 | M3: 36 | N3: 7 | O3: 1.8
A4: 01-Jan-2025 | B4: W01 | C4: Facebook | D4: Community / Cultural | E4: End of financial year, our journey | F4: 3226 | G4: 3904 | H4: 42 | I4: 5 | J4: 6 | K4: 7 | L4: 216 | M4: 57 | N4: 15 | O4: 1.96
A5: 02-Jan-2025 | B5: W01 | C5: Instagram | D5: Educational | E5: 5 ways to save with mobile money | F5: 4247 | G5: 6385 | H5: 95 | I5: 26 | J5: 11 | K5: 15 | L5: 451 | M5: 173 | N5: 22 | O5: 3.57
A6: 02-Jan-2025 | B6: W01 | C6: TikTok | D6: Product Feature | E6: International transfers, step by step | F6: 1916 | G6: 2741 | H6: 82 | I6: 19 | J6: 13 | K6: 10 | L6: 146 | M6: 99 | N6: 12 | O6: 6.16
A7: 03-Jan-2025 | B7: W01 | C7: Facebook | D7: Behind the Scenes | E7: PesaPal turns 5, the early days | F7: 1021 | G7: 1447 | H7: 8 | I7: 1 | J7: 1 | K7: 2 | L7: 97 | M7: 21 | N7: 5 | O7: 1.49
A8: 03-Jan-2025 | B8: W01 | C8: LinkedIn | D8: Community / Cultural | E8: #NjaaaKwetuChallenge, save together | F8: 1029 | G8: 1148 | H8: 20 | I8: 3 | J8: 3 | K8: 4 | L8: 67 | M8: 44 | N8: 3 | O8: 3.33
A9: 04-Jan-2025 | B9: W01 | C9: LinkedIn | D9: Educational | E9: Digital wallet security tips | F9: 1598 | G9: 1967 | H9: 43 | I9: 7 | J9: 4 | K9: 9 | L9: 129 | M9: 23 | N9: 0 | O9: 3.97
A10: 04-Jan-2025 | B10: W01 | C10: Instagram | D10: Educational | E10: Digital wallet security tips | F10: 1948 | G10: 2805 | H10: 36 | I10: 8 | J10: 4 | K10: 4 | L10: 164 | M10: 111 | N10: 18 | O10: 3.12
A11: 04-Jan-2025 | B11: W01 | C11: TikTok | D11: Educational | E11: Understanding transaction fees | F11: 9879 | G11: 14663 | H11: 270 | I11: 43 | J11: 22 | K11: 55 | L11: 963 | M11: 578 | N11: 49 | O11: 4.62 | P11: Possible viral reach spike
A12: 05-Jan-2025 | B12: W01 | C12: Instagram | D12: Promotional | E12: Limited time sign-up bonus | F12: 1874 | G12: 2247 | H12: 12 | I12: 3 | J12: 2 | K12: 3 | L12: 164 | M12: 64 | N12: 2 | O12: 1.19 | P12: Low engagement, promo fatigue
A13: 05-Jan-2025 | B13: W01 | C13: Facebook | D13: Promotional | E13: New year new wallet offer | F13: 855 | G13: 1043 | H13: 3 | I13: 1 | J13: 0 | K13: 1 | L13: 70 | M13: 13 | N13: 4 | O13: 0.84 | P13: Low engagement, promo fatigue
A14: 06-Jan-2025 | B14: W01 | C14: TikTok | D14: Behind the Scenes | E14: The team behind your midnight transactions | F14: 9218 | G14: 13319 | H14: 385 | I14: 93 | J14: 48 | K14: 88 | L14: 701 | M14: 206 | N14: 9 | O14: 6.86 | P14: Possible viral reach spike
A15: 06-Jan-2025 | B15: W01 | C15: LinkedIn | D15: Educational | E15: Understanding transaction fees | F15: 903 | G15: 1092 | H15: 10 | I15: 1 | J15: 1 | K15: 2 | L15: 41 | M15: 19 | N15: 5 | O15: 1.96
A16: 06-Jan-2025 | B16: W01 | C16: Facebook | D16: Promotional | E16: Refer a friend get KSh 100 | F16: 1736 | G16: 2675 | H16: 8 | I16: 1 | J16: 1 | K16: 0 | L16: 160 | M16: 48 | N16: 3 | O16: 0.84 | P16: Low engagement, promo fatigue
A17: 07-Jan-2025 | B17: W01 | C17: Instagram | D17: Educational | E17: Digital wallet security tips | F17: 2877 | G17: 4404 | H17: 32 | I17: 6 | J17: 4 | K17: 4 | L17: 172 | M17: 161 | N17: 12 | O17: 1.96
A18: 07-Jan-2025 | B18: W01 | C18: Facebook | D18: Behind the Scenes | E18: The team behind your midnight transactions | F18: 1110 | G18: 1582 | H18: 8 | I18: 1 | J18: 1 | K18: 1 | L18: 80 | M18: 37 | N18: 11 | O18: 1.5
A19: 07-Jan-2025 | B19: W01 | C19: LinkedIn | D19: Behind the Scenes | E19: How we built the new savings feature | F19: 1128 | G19: 1796 | H19: 18 | I19: 3 | J19: 2 | K19: 4 | L19: 134 | M19: 42 | N19: 5 | O19: 2.53
A20: 08-Jan-2025 | B20: W02 | C20: Facebook | D20: Promotional | E20: Fagiafest offer, zero transfer fees | F20: 1474 | G20: 2020 | H20: 7 | I20: 1 | J20: 1 | K20: 1 | L20: 77 | M20: 85 | N20: 1 | O20: 1.01 | P20: Low engagement, promo fatigue
A21: 09-Jan-2025 | B21: W02 | C21: Instagram | D21: Product Feature | E21: Split payments feature launch | F21: 2523 | G21: 3963 | H21: 38 | I21: 5 | J21: 3 | K21: 6 | L21: 215 | M21: 65 | N21: 6 | O21: 2.38
A22: 10-Jan-2025 | B22: W02 | C22: Facebook | D22: Promotional | E22: Refer a friend get KSh 100 | F22: 1642 | G22: 2052 | H22: 5 | I22: 0 | J22: 0 | K22: 1 | L22: 196 | M22: 22 | N22: 2 | O22: 0.59 | P22: Low engagement, promo fatigue
A23: 10-Jan-2025 | B23: W02 | C23: Instagram | D23: Promotional | E23: New year new wallet offer | F23: 2841 | G23: 4374 | H23: 18 | I23: 5 | J23: 3 | K23: 3 | L23: 338 | M23: 121 | N23: 1 | O23: 1.18 | P23: Low engagement, promo fatigue
A24: 11-Jan-2025 | B24: W02 | C24: Facebook | D24: Behind the Scenes | E24: How we built the new savings feature | F24: 1673 | G24: 2584 | H24: 17 | I24: 3 | J24: 2 | K24: 2 | L24: 158 | M24: 88 | N24: 7 | O24: 1.87
A25: 11-Jan-2025 | B25: W02 | C25: LinkedIn | D25: Promotional | E25: Fagiafest offer, zero transfer fees | F25: 306 | G25: 401 | H25: 2 | I25: 0 | J25: 0 | K25: 0 | L25: 30 | M25: 11 | N25: 1 | O25: 1.38
A26: 11-Jan-2025 | B26: W02 | C26: Instagram | D26: Educational | E26: How M-PESA limits work | F26: 6015 | G26: 8694 | H26: 53 | I26: 11 | J26: 8 | K26: 9 | L26: 260 | M26: 169 | N26: 23 | O26: 1.62
A27: 12-Jan-2025 | B27: W02 | C27: Instagram | D27: Product Feature | E27: International transfers, step by step | F27: 1298 | G27: 1934 | H27: 25 | I27: 5 | J27: 2 | K27: 5 | L27: 141 | M27: 76 | N27: 16 | O27: 3.21
A28: 12-Jan-2025 | B28: W02 | C28: TikTok | D28: Behind the Scenes | E28: Meet our customer support team in Nairobi | F28: 3378 | G28: 5277 | H28: 151 | I28: 36 | J28: 25 | K28: 18 | L28: 178 | M28: 152 | N28: 26 | O28: 7.34
A29: 12-Jan-2025 | B29: W02 | C29: LinkedIn | D29: Educational | E29: Sending money abroad safely | F29: 887 | G29: 1337 | H29: 17 | I29: 4 | J29: 1 | K29: 1 | L29: 49 | M29: 23 | N29: 7 | O29: 3.48
A30: 13-Jan-2025 | B30: W02 | C30: Facebook | D30: Product Feature | E30: Business accounts, what's different | F30: 1607 | G30: 1789 | H30: 16 | I30: 3 | J30: 3 | K30: 1 | L30: 140 | M30: 43 | N30: 8 | O30: 1.79
A31: 13-Jan-2025 | B31: W02 | C31: TikTok | D31: UGC / Testimonial | E31: University student budgeting with PesaPal | F31: 3783 | G31: 5862 | H31: 94 | I31: 21 | J31: 14 | K31: 22 | L31: 359 | M31: 215 | N31: 62 | O31: 4.51 | P31: High performer, amplify this
A32: 13-Jan-2025 | B32: W02 | C32: LinkedIn | D32: Educational | E32: Sending money abroad safely | F32: 566 | G32: 810 | H32: 9 | I32: 2 | J32: 1 | K32: 1 | L32: 36 | M32: 17 | N32: 3 | O32: 2.97
A33: 14-Jan-2025 | B33: W02 | C33: TikTok | D33: Educational | E33: Digital wallet security tips | F33: 11948 | G33: 17189 | H33: 675 | I33: 115 | J33: 92 | K33: 52 | L33: 752 | M33: 376 | N33: 39 | O33: 8.8 | P33: Possible viral reach spike
A34: 15-Jan-2025 | B34: W03 | C34: LinkedIn | D34: UGC / Testimonial | E34: Mama mboga grows her business with PesaPal | F34: 1920 | G34: 2873 | H34: 88 | I34: 19 | J34: 9 | K34: 15 | L34: 171 | M34: 28 | N34: 10 | O34: 7 | P34: High performer, amplify this
A35: 15-Jan-2025 | B35: W03 | C35: TikTok | D35: Promotional | E35: New year new wallet offer | F35: 2066 | G35: 2478 | H35: 13 | I35: 2 | J35: 2 | K35: 1 | L35: 151 | M35: 85 | N35: 8 | O35: 1.14 | P35: Low engagement, promo fatigue
A36: 16-Jan-2025 | B36: W03 | C36: LinkedIn | D36: Promotional | E36: Limited time sign-up bonus | F36: 932 | G36: 1441 | H36: 15 | I36: 3 | J36: 1 | K36: 2 | L36: 89 | M36: 30 | N36: 2 | O36: 2.53
A37: 16-Jan-2025 | B37: W03 | C37: TikTok | D37: Behind the Scenes | E37: Meet our customer support team in Nairobi | F37: 6188 | G37: 9286 | H37: 282 | I37: 56 | J37: 47 | K37: 56 | L37: 550 | M37: 284 | N37: 32 | O37: 6.55 | P37: Possible viral reach spike
A38: 17-Jan-2025 | B38: W03 | C38: LinkedIn | D38: UGC / Testimonial | E38: Mama mboga grows her business with PesaPal | F38: 2807 | G38: 3476 | H38: 105 | I38: 17 | J38: 13 | K38: 20 | L38: 164 | M38: 75 | N38: 9 | O38: 6.08 | P38: High performer, amplify this
A39: 17-Jan-2025 | B39: W03 | C39: Instagram | D39: Educational | E39: What is a credit score? | F39: 2317 | G39: 3352 | H39: 44 | I39: 9 | J39: 7 | K39: 7 | L39: 131 | M39: 71 | N39: 23 | O39: 3.49
A40: 17-Jan-2025 | B40: W03 | C40: TikTok | D40: Product Feature | E40: International transfers, step by step | F40: 1487 | G40: 2290 | H40: 45 | I40: 12 | J40: 5 | K40: 6 | L40: 165 | M40: 77 | N40: 29 | O40: 5.01
A41: 18-Jan-2025 | B41: W03 | C41: TikTok | D41: Promotional | E41: Valentine's cashback campaign | F41: 3491 | G41: 4518 | H41: 82 | I41: 18 | J41: 13 | K41: 17 | L41: 413 | M41: 128 | N41: 28 | O41: 3.53
A42: 18-Jan-2025 | B42: W03 | C42: LinkedIn | D42: Product Feature | E42: International transfers, step by step | F42: 374 | G42: 531 | H42: 3 | I42: 0 | J42: 0 | K42: 0 | L42: 24 | M42: 17 | N42: 2 | O42: 1.74
A43: 19-Jan-2025 | B43: W03 | C43: LinkedIn | D43: Community / Cultural | E43: PesaPal x Nairobi marathon partnership | F43: 526 | G43: 720 | H43: 19 | I43: 4 | J43: 3 | K43: 3 | L43: 52 | M43: 30 | N43: 1 | O43: 6.4
A44: 19-Jan-2025 | B44: W03 | C44: TikTok | D44: Educational | E44: What is a credit score? | F44: 4284 | G44: 5726 | H44: 87 | I44: 15 | J44: 8 | K44: 10 | L44: 379 | M44: 249 | N44: 47 | O44: 2.95
A45: 20-Jan-2025 | B45: W03 | C45: TikTok | D45: Educational | E45: How M-PESA limits work | F45: 11823 | G45: 16409 | H45: 633 | I45: 181 | J45: 66 | K45: 114 | L45: 1258 | M45: 261 | N45: 46 | O45: 8.84 | P45: Possible viral reach spike
A46: 20-Jan-2025 | B46: W03 | C46: LinkedIn | D46: Promotional | E46: Limited time sign-up bonus | F46: 840 | G46: 974 | H46: 15 | I46: 2 | J46: 1 | K46: 2 | L46: 67 | M46: 22 | N46: 3 | O46: 2.77
A47: 21-Jan-2025 | B47: W03 | C47: Instagram | D47: Product Feature | E47: Instant loans, eligibility explained | F47: 3758 | G47: 4952 | H47: 72 | I47: 11 | J47: 11 | K47: 10 | L47: 295 | M47: 119 | N47: 15 | O47: 2.82
A48: 21-Jan-2025 | B48: W03 | C48: TikTok | D48: Promotional | E48: Refer a friend get KSh 100 | F48: 5375 | G48: 6145 | H48: 136 | I48: 29 | J48: 21 | K48: 20 | L48: 227 | M48: 282 | N48: 8 | O48: 4.32
A49: 21-Jan-2025 | B49: W03 | C49: Facebook | D49: Promotional | E49: New year new wallet offer | F49: 1039 | G49: 1600 | H49: 5 | I49: 0 | J49: 1 | K49: 0 | L49: 101 | M49: 35 | N49: 5 | O49: 0.97 | P49: Low engagement, promo fatigue
A50: 22-Jan-2025 | B50: W04 | C50: LinkedIn | D50: Community / Cultural | E50: #NjaaaKwetuChallenge, save together | F50: 1186 | G50: 1544 | H50: 22 | I50: 4 | J50: 3 | K50: 2 | L50: 142 | M50: 44 | N50: 3 | O50: 3.01
A51: 22-Jan-2025 | B51: W04 | C51: TikTok | D51: UGC / Testimonial | E51: 'I sent money to my village in 3 taps' | F51: 5689 | G51: 6601 | H51: 146 | I51: 34 | J51: 26 | K51: 17 | L51: 326 | M51: 194 | N51: 61 | O51: 4.54 | P51: High performer, amplify this
A52: 23-Jan-2025 | B52: W04 | C52: Facebook | D52: Promotional | E52: New year new wallet offer | F52: 746 | G52: 825 | H52: 2 | I52: 0 | J52: 0 | K52: 0 | L52: 37 | M52: 39 | N52: 3 | O52: 0.8 | P52: Low engagement, promo fatigue
A53: 23-Jan-2025 | B53: W04 | C53: Instagram | D53: Behind the Scenes | E53: The team behind your midnight transactions | F53: 2407 | G53: 3223 | H53: 34 | I53: 5 | J53: 5 | K53: 3 | L53: 108 | M53: 83 | N53: 14 | O53: 2.1
A54: 23-Jan-2025 | B54: W04 | C54: LinkedIn | D54: Product Feature | E54: Split payments feature launch | F54: 576 | G54: 795 | H54: 9 | I54: 1 | J54: 1 | K54: 1 | L54: 59 | M54: 12 | N54: 3 | O54: 2.26
A55: 24-Jan-2025 | B55: W04 | C55: LinkedIn | D55: Behind the Scenes | E55: Our Westlands office, a quick tour | F55: 985 | G55: 1389 | H55: 24 | I55: 6 | J55: 2 | K55: 2 | L55: 91 | M55: 17 | N55: 1 | O55: 3.78
A56: 24-Jan-2025 | B56: W04 | C56: TikTok | D56: Educational | E56: How M-PESA limits work | F56: 6141 | G56: 8871 | H56: 190 | I56: 37 | J56: 23 | K56: 46 | L56: 280 | M56: 133 | N56: 21 | O56: 5.59 | P56: Possible viral reach spike
A57: 25-Jan-2025 | B57: W04 | C57: TikTok | D57: Educational | E57: What is a credit score? | F57: 8752 | G57: 13602 | H57: 403 | I57: 69 | J57: 51 | K57: 89 | L57: 748 | M57: 213 | N57: 13 | O57: 8.23 | P57: Possible viral reach spike
A58: 25-Jan-2025 | B58: W04 | C58: LinkedIn | D58: Product Feature | E58: International transfers, step by step | F58: 994 | G58: 1228 | H58: 17 | I58: 4 | J58: 3 | K58: 3 | L58: 87 | M58: 11 | N58: 1 | O58: 2.98
A59: 26-Jan-2025 | B59: W04 | C59: Instagram | D59: Community / Cultural | E59: Easter weekend, shop local with PesaPal | F59: 1518 | G59: 2243 | H59: 29 | I59: 7 | J59: 2 | K59: 4 | L59: 137 | M59: 52 | N59: 5 | O59: 3.09
A60: 26-Jan-2025 | B60: W04 | C60: Facebook | D60: Promotional | E60: New year new wallet offer | F60: 1004 | G60: 1156 | H60: 2 | I60: 0 | J60: 0 | K60: 0 | L60: 101 | M60: 11 | N60: 1 | O60: 0.44 | P60: Low engagement, promo fatigue
A61: 27-Jan-2025 | B61: W04 | C61: Instagram | D61: Behind the Scenes | E61: Our Westlands office, a quick tour | F61: 5200 | G61: 7864 | H61: 36 | I61: 6 | J61: 2 | K61: 5 | L61: 467 | M61: 181 | N61: 11 | O61: 1.04
A62: 28-Jan-2025 | B62: W04 | C62: Facebook | D62: Product Feature | E62: Savings goal tracker, how to set one | F62: 1913 | G62: 2772 | H62: 8 | I62: 1 | J62: 0 | K62: 0 | L62: 160 | M62: 71 | N62: 2 | O62: 0.63
A63: 29-Jan-2025 | B63: W05 | C63: Instagram | D63: Product Feature | E63: Split payments feature launch | F63: 2908 | G63: 4240 | H63: 37 | I63: 10 | J63: 7 | K63: 4 | L63: 244 | M63: 84 | N63: 18 | O63: 2.22
A64: 29-Jan-2025 | B64: W05 | C64: TikTok | D64: UGC / Testimonial | E64: Mama mboga grows her business with PesaPal | F64: 14290 | G64: 17692 | H64: 895 | I64: 253 | J64: 125 | K64: 193 | L64: 894 | M64: 356 | N64: 51 | O64: 10.24 | P64: High performer, amplify this
A65: 29-Jan-2025 | B65: W05 | C65: LinkedIn | D65: Behind the Scenes | E65: Our Westlands office, a quick tour | F65: 2077 | G65: 2748 | H65: 40 | I65: 10 | J65: 5 | K65: 9 | L65: 227 | M65: 122 | N65: 1 | O65: 3.32
A66: 30-Jan-2025 | B66: W05 | C66: LinkedIn | D66: Promotional | E66: Valentine's cashback campaign | F66: 950 | G66: 1430 | H66: 9 | I66: 2 | J66: 1 | K66: 1 | L66: 40 | M66: 33 | N66: 2 | O66: 1.6
A67: 30-Jan-2025 | B67: W05 | C67: Instagram | D67: Behind the Scenes | E67: Our Westlands office, a quick tour | F67: 1519 | G67: 2362 | H67: 9 | I67: 2 | J67: 1 | K67: 0 | L67: 155 | M67: 35 | N67: 15 | O67: 1.09
A68: 31-Jan-2025 | B68: W05 | C68: Instagram | D68: Behind the Scenes | E68: The team behind your midnight transactions | F68: 2867 | G68: 3607 | H68: 62 | I68: 15 | J68: 4 | K68: 5 | L68: 259 | M68: 160 | N68: 23 | O68: 3.28
A69: 31-Jan-2025 | B69: W05 | C69: TikTok | D69: Community / Cultural | E69: PesaPal x Nairobi marathon partnership | F69: 14129 | G69: 20913 | H69: 667 | I69: 114 | J69: 83 | K69: 62 | L69: 931 | M69: 180 | N69: 30 | O69: 8.37 | P69: Possible viral reach spike
A70: 01-Feb-2025 | B70: W05 | C70: TikTok | D70: UGC / Testimonial | E70: Small business owner, rent day sorted | F70: 13286 | G70: 15743 | H70: 311 | I70: 65 | J70: 30 | K70: 64 | L70: 683 | M70: 439 | N70: 27 | O70: 3.45 | P70: Possible viral reach spike
A71: 01-Feb-2025 | B71: W05 | C71: Facebook | D71: Promotional | E71: Fagiafest offer, zero transfer fees | F71: 2056 | G71: 2739 | H71: 6 | I71: 0 | J71: 1 | K71: 1 | L71: 131 | M71: 119 | N71: 5 | O71: 0.56 | P71: Low engagement, promo fatigue
A72: 02-Feb-2025 | B72: W05 | C72: Facebook | D72: Behind the Scenes | E72: Our Westlands office, a quick tour | F72: 1140 | G72: 1471 | H72: 7 | I72: 1 | J72: 0 | K72: 1 | L72: 81 | M72: 11 | N72: 11 | O72: 1.17
A73: 02-Feb-2025 | B73: W05 | C73: Instagram | D73: Community / Cultural | E73: #NjaaaKwetuChallenge, save together | F73: 6670 | G73: 9822 | H73: 204 | I73: 46 | J73: 19 | K73: 38 | L73: 383 | M73: 130 | N73: 9 | O73: 4.48
A74: 03-Feb-2025 | B74: W05 | C74: TikTok | D74: Educational | E74: Digital wallet security tips | F74: 8738 | G74: 10961 | H74: 298 | I74: 71 | J74: 26 | K74: 37 | L74: 872 | M74: 164 | N74: 14 | O74: 5.37 | P74: Possible viral reach spike
A75: 03-Feb-2025 | B75: W05 | C75: Facebook | D75: Product Feature | E75: Savings goal tracker, how to set one | F75: 2178 | G75: 3390 | H75: 21 | I75: 6 | J75: 3 | K75: 4 | L75: 217 | M75: 58 | N75: 2 | O75: 1.72
A76: 04-Feb-2025 | B76: W05 | C76: TikTok | D76: Behind the Scenes | E76: The team behind your midnight transactions | F76: 5268 | G76: 7877 | H76: 67 | I76: 13 | J76: 10 | K76: 12 | L76: 457 | M76: 269 | N76: 55 | O76: 2.05
A77: 04-Feb-2025 | B77: W05 | C77: Instagram | D77: Educational | E77: What is a credit score? | F77: 3562 | G77: 5021 | H77: 91 | I77: 21 | J77: 14 | K77: 17 | L77: 274 | M77: 160 | N77: 17 | O77: 4.29
A78: 04-Feb-2025 | B78: W05 | C78: LinkedIn | D78: Educational | E78: How M-PESA limits work | F78: 2407 | G78: 3014 | H78: 48 | I78: 14 | J78: 5 | K78: 8 | L78: 225 | M78: 113 | N78: 7 | O78: 3.61
A79: 05-Feb-2025 | B79: W06 | C79: TikTok | D79: Product Feature | E79: Instant loans, eligibility explained | F79: 6602 | G79: 10362 | H79: 141 | I79: 21 | J79: 17 | K79: 15 | L79: 455 | M79: 389 | N79: 21 | O79: 3.28 | P79: Possible viral reach spike
A80: 05-Feb-2025 | B80: W06 | C80: LinkedIn | D80: Behind the Scenes | E80: PesaPal turns 5, the early days | F80: 1089 | G80: 1414 | H80: 13 | I80: 3 | J80: 1 | K80: 2 | L80: 99 | M80: 43 | N80: 0 | O80: 2.25
A81: 06-Feb-2025 | B81: W06 | C81: TikTok | D81: Community / Cultural | E81: Celebrating Madaraka Day with free transfers | F81: 2776 | G81: 4115 | H81: 66 | I81: 19 | J81: 8 | K81: 7 | L81: 311 | M81: 28 | N81: 62 | O81: 4.16
A82: 06-Feb-2025 | B82: W06 | C82: Instagram | D82: Educational | E82: What is a credit score? | F82: 3918 | G82: 5874 | H82: 39 | I82: 5 | J82: 4 | K82: 7 | L82: 341 | M82: 42 | N82: 8 | O82: 1.49
A83: 07-Feb-2025 | B83: W06 | C83: LinkedIn | D83: UGC / Testimonial | E83: Small business owner, rent day sorted | F83: 711 | G83: 941 | H83: 17 | I83: 3 | J83: 1 | K83: 3 | L83: 69 | M83: 39 | N83: 7 | O83: 3.98
A84: 08-Feb-2025 | B84: W06 | C84: Instagram | D84: Behind the Scenes | E84: Our Westlands office, a quick tour | F84: 3090 | G84: 3565 | H84: 61 | I84: 16 | J84: 7 | K84: 6 | L84: 154 | M84: 127 | N84: 14 | O84: 3.26
A85: 08-Feb-2025 | B85: W06 | C85: LinkedIn | D85: Community / Cultural | E85: PesaPal x Nairobi marathon partnership | F85: 2867 | G85: 3914 | H85: 72 | I85: 10 | J85: 11 | K85: 15 | L85: 263 | M85: 138 | N85: 6 | O85: 3.95
A86: 09-Feb-2025 | B86: W06 | C86: LinkedIn | D86: Behind the Scenes | E86: Our Westlands office, a quick tour | F86: 1050 | G86: 1393 | H86: 18 | I86: 3 | J86: 3 | K86: 2 | L86: 54 | M86: 58 | N86: 0 | O86: 3.07
A87: 10-Feb-2025 | B87: W06 | C87: Instagram | D87: Community / Cultural | E87: Supporting Kenyan SMEs this month | F87: 6085 | G87: 8386 | H87: 135 | I87: 24 | J87: 12 | K87: 18 | L87: 567 | M87: 289 | N87: 25 | O87: 3.53
A88: 10-Feb-2025 | B88: W06 | C88: TikTok | D88: Community / Cultural | E88: Supporting Kenyan SMEs this month | F88: 9413 | G88: 12009 | H88: 399 | I88: 100 | J88: 45 | K88: 41 | L88: 1013 | M88: 267 | N88: 56 | O88: 7.3 | P88: Possible viral reach spike
A89: 10-Feb-2025 | B89: W06 | C89: LinkedIn | D89: Product Feature | E89: Instant loans, eligibility explained | F89: 1724 | G89: 2736 | H89: 42 | I89: 9 | J89: 3 | K89: 9 | L89: 183 | M89: 40 | N89: 1 | O89: 3.84
A90: 11-Feb-2025 | B90: W06 | C90: Facebook | D90: Promotional | E90: Refer a friend get KSh 100 | F90: 2003 | G90: 2770 | H90: 7 | I90: 1 | J90: 0 | K90: 1 | L90: 114 | M90: 62 | N90: 2 | O90: 0.67 | P90: Low engagement, promo fatigue
A91: 11-Feb-2025 | B91: W06 | C91: TikTok | D91: Promotional | E91: Limited time sign-up bonus | F91: 2611 | G91: 4101 | H91: 58 | I91: 8 | J91: 8 | K91: 4 | L91: 121 | M91: 83 | N91: 15 | O91: 3.26
A92: 12-Feb-2025 | B92: W07 | C92: LinkedIn | D92: Promotional | E92: End of month bonus interest | F92: 329 | G92: 432 | H92: 2 | I92: 0 | J92: 0 | K92: 0 | L92: 23 | M92: 13 | N92: 0 | O92: 1.4
A93: 12-Feb-2025 | B93: W07 | C93: TikTok | D93: Promotional | E93: Refer a friend get KSh 100 | F93: 5029 | G93: 7453 | H93: 60 | I93: 13 | J93: 8 | K93: 6 | L93: 415 | M93: 108 | N93: 19 | O93: 2.12
A94: 13-Feb-2025 | B94: W07 | C94: Facebook | D94: UGC / Testimonial | E94: Small business owner, rent day sorted | F94: 1277 | G94: 1416 | H94: 25 | I94: 5 | J94: 3 | K94: 4 | L94: 93 | M94: 20 | N94: 2 | O94: 3.04
A95: 13-Feb-2025 | B95: W07 | C95: Instagram | D95: Promotional | E95: End of month bonus interest | F95: 1751 | G95: 2529 | H95: 12 | I95: 1 | J95: 1 | K95: 1 | L95: 81 | M95: 93 | N95: 9 | O95: 1.17 | P95: Low engagement, promo fatigue
A96: 14-Feb-2025 | B96: W07 | C96: TikTok | D96: Educational | E96: Digital wallet security tips | F96: 2925 | G96: 3963 | H96: 154 | I96: 39 | J96: 27 | K96: 33 | L96: 172 | M96: 50 | N96: 18 | O96: 8.82
A97: 15-Feb-2025 | B97: W07 | C97: Instagram | D97: Behind the Scenes | E97: PesaPal turns 5, the early days | F97: 3416 | G97: 5046 | H97: 71 | I97: 20 | J97: 10 | K97: 13 | L97: 307 | M97: 181 | N97: 15 | O97: 3.41
A98: 15-Feb-2025 | B98: W07 | C98: LinkedIn | D98: Educational | E98: How M-PESA limits work | F98: 1404 | G98: 1987 | H98: 42 | I98: 7 | J98: 3 | K98: 6 | L98: 60 | M98: 39 | N98: 2 | O98: 4.8
A99: 16-Feb-2025 | B99: W07 | C99: Instagram | D99: Product Feature | E99: Instant loans, eligibility explained | F99: 2763 | G99: 3805 | H99: 56 | I99: 10 | J99: 8 | K99: 9 | L99: 181 | M99: 93 | N99: 4 | O99: 2.97
A100: 16-Feb-2025 | B100: W07 | C100: Facebook | D100: Educational | E100: How M-PESA limits work | F100: 3791 | G100: 5757 | H100: 52 | I100: 13 | J100: 4 | K100: 11 | L100: 452 | M100: 137 | N100: 9 | O100: 2.49
...

Sheet Summary Dashboard
A1: PesaPal Kenya - 90-Day Social Media Performance Dashboard
A2: Period: 1 January 2025 – 31 March 2025 | Platforms: Instagram, TikTok, Facebook, LinkedIn | Brand: PesaPal Kenya
A4: SECTION 1 - OVERALL CAMPAIGN KPIs (All Platforms Combined)
A5: Metric | B5: Value | D5: Metric | E5: Value
A6: Total Posts Published | B6: =COUNTA('Raw Data'!A3:A179) -> 177 | D6: Total Reach | E6: =SUM('Raw Data'!F3:F179) -> 568466
A7: Total Impressions | B7: =SUM('Raw Data'!G3:G179) -> 781707 | D7: Total Likes | E7: =SUM('Raw Data'!H3:H179) -> 14304
A8: Total Comments | B8: =SUM('Raw Data'!I3:I179) -> 2984 | D8: Total Shares | E8: =SUM('Raw Data'!J3:J179) -> 1854
A9: Total Saves | B9: =SUM('Raw Data'!K3:K179) -> 2282 | D9: Total Link Clicks | E9: =SUM('Raw Data'!M3:M179) -> 20379
A10: Total New Followers | B10: =SUM('Raw Data'!N3:N179) -> 2419 | D10: Avg Engagement Rate | E10: =AVERAGE('Raw Data'!O3:O179) -> 3.1314689
A12: SECTION 2 - PLATFORM BREAKDOWN
A13: Platform | B13: Posts | C13: Avg Reach | D13: Avg Eng Rate (%) | E13: Total Followers | F13: Best Content Type
A14: Instagram | B14: =COUNTIF('Raw Data'!C3:C179,"Instagram") -> 45 | C14: =AVERAGEIF('Raw Data'!C3:C179,"Instagram",'Raw Data'!F3:F179) -> 3105.6222 | D14: =AVERAGEIF('Raw Data'!C3:C179,"Instagram",'Raw Data'!O3:O179) -> 2.3782222 | E14: =SUMIF('Raw Data'!C3:C179,"Instagram",'Raw Data'!N3:N179) -> 570 | F14: UGC / Testimonial
A15: TikTok | B15: =COUNTIF('Raw Data'!C3:C179,"TikTok") -> 45 | C15: =AVERAGEIF('Raw Data'!C3:C179,"TikTok",'Raw Data'!F3:F179) -> 6229.5778 | D15: =AVERAGEIF('Raw Data'!C3:C179,"TikTok",'Raw Data'!O3:O179) -> 5.206 | E15: =SUMIF('Raw Data'!C3:C179,"TikTok",'Raw Data'!N3:N179) -> 1400 | F15: Community / Cultural
A16: Facebook | B16: =COUNTIF('Raw Data'!C3:C179,"Facebook") -> 41 | C16: =AVERAGEIF('Raw Data'!C3:C179,"Facebook",'Raw Data'!F3:F179) -> 2185.6585 | D16: =AVERAGEIF('Raw Data'!C3:C179,"Facebook",'Raw Data'!O3:O179) -> 1.4429268 | E16: =SUMIF('Raw Data'!C3:C179,"Facebook",'Raw Data'!N3:N179) -> 288 | F16: Educational
A17: LinkedIn | B17: =COUNTIF('Raw Data'!C3:C179,"LinkedIn") -> 46 | C17: =AVERAGEIF('Raw Data'!C3:C179,"LinkedIn",'Raw Data'!F3:F179) -> 1277.6087 | D17: =AVERAGEIF('Raw Data'!C3:C179,"LinkedIn",'Raw Data'!O3:O179) -> 3.343913 | E17: =SUMIF('Raw Data'!C3:C179,"LinkedIn",'Raw Data'!N3:N179) -> 161 | F17: Product Feature
A20: SECTION 3 - CONTENT TYPE PERFORMANCE
A21: Content Type | B21: Posts | C21: Avg Reach | D21: Avg Eng Rate (%) | E21: Avg Followers Gained | F21: Assessment
A22: Educational | B22: =COUNTIF('Raw Data'!D3:D179,"Educational") -> 40 | C22: =AVERAGEIF('Raw Data'!D3:D179,"Educational",'Raw Data'!F3:F179) -> 3916.975 | D22: =AVERAGEIF('Raw Data'!D3:D179,"Educational",'Raw Data'!O3:O179) -> 3.8005 | E22: =AVERAGEIF('Raw Data'!D3:D179,"Educational",'Raw Data'!N3:N179) -> 16.525 | F22: Consistent performer, high save rate
A23: Promotional | B23: =COUNTIF('Raw Data'!D3:D179,"Promotional") -> 37 | C23: =AVERAGEIF('Raw Data'!D3:D179,"Promotional",'Raw Data'!F3:F179) -> 1780.5405 | D23: =AVERAGEIF('Raw Data'!D3:D179,"Promotional",'Raw Data'!O3:O179) -> 1.5597297 | E23: =AVERAGEIF('Raw Data'!D3:D179,"Promotional",'Raw Data'!N3:N179) -> 5.7567568 | F23: Lowest engagement, reduce frequency
A24: UGC / Testimonial | B24: =COUNTIF('Raw Data'!D3:D179,"UGC / Testimonial") -> 21 | C24: =AVERAGEIF('Raw Data'!D3:D179,"UGC / Testimonial",'Raw Data'!F3:F179) -> 4671 | D24: =AVERAGEIF('Raw Data'!D3:D179,"UGC / Testimonial",'Raw Data'!O3:O179) -> 4.157619 | E24: =AVERAGEIF('Raw Data'!D3:D179,"UGC / Testimonial",'Raw Data'!N3:N179) -> 20.952381 | F24: Top performer, scale this format
A25: Product Feature | B25: =COUNTIF('Raw Data'!D3:D179,"Product Feature") -> 33 | C25: =AVERAGEIF('Raw Data'!D3:D179,"Product Feature",'Raw Data'!F3:F179) -> 2489.0303 | D25: =AVERAGEIF('Raw Data'!D3:D179,"Product Feature",'Raw Data'!O3:O179) -> 2.6660606 | E25: =AVERAGEIF('Raw Data'!D3:D179,"Product Feature",'Raw Data'!N3:N179) -> 12.787879 | F25: Mid-tier, improve with demos
A26: Community / Cultural | B26: =COUNTIF('Raw Data'!D3:D179,"Community / Cultural") -> 19 | C26: =AVERAGEIF('Raw Data'!D3:D179,"Community / Cultural",'Raw Data'!F3:F179) -> 4352.7368 | D26: =AVERAGEIF('Raw Data'!D3:D179,"Community / Cultural",'Raw Data'!O3:O179) -> 3.9110526 | E26: =AVERAGEIF('Raw Data'!D3:D179,"Community / Cultural",'Raw Data'!N3:N179) -> 16.578947 | F26: Strong reach, culturally resonant
A27: Behind the Scenes | B27: =COUNTIF('Raw Data'!D3:D179,"Behind the Scenes") -> 27 | C27: =AVERAGEIF('Raw Data'!D3:D179,"Behind the Scenes",'Raw Data'!F3:F179) -> 3073.1852 | D27: =AVERAGEIF('Raw Data'!D3:D179,"Behind the Scenes",'Raw Data'!O3:O179) -> 3.5162963 | E27: =AVERAGEIF('Raw Data'!D3:D179,"Behind the Scenes",'Raw Data'!N3:N179) -> 13.62963 | F27: Underused but high engagement when posted
A30: SECTION 4 - WEEKLY TREND (Total Reach by Week)
A31: Week | B31: Total Reach | C31: Total Posts | D31: Avg Eng Rate (%) | E31: New Followers | F31: Trend Note
A32: W01 | B32: =SUMIF('Raw Data'!B3:B179,"W01",'Raw Data'!F3:F179) -> 45486 | C32: =COUNTIF('Raw Data'!B3:B179,"W01") -> 17 | D32: =AVERAGEIF('Raw Data'!B3:B179,"W01",'Raw Data'!O3:O179) -> 2.8058824 | E32: =SUMIF('Raw Data'!B3:B179,"W01",'Raw Data'!N3:N179) -> 182 | F32: Baseline week, low posting volume
A33: W02 | B33: =SUMIF('Raw Data'!B3:B179,"W02",'Raw Data'!F3:F179) -> 39941 | C33: =COUNTIF('Raw Data'!B3:B179,"W02") -> 14 | D33: =AVERAGEIF('Raw Data'!B3:B179,"W02",'Raw Data'!O3:O179) -> 3.0092857 | E33: =SUMIF('Raw Data'!B3:B179,"W02",'Raw Data'!N3:N179) -> 202 | F33: UGC campaign launched, reach spike
A34: W03 | B34: =SUMIF('Raw Data'!B3:B179,"W03",'Raw Data'!F3:F179) -> 49227 | C34: =COUNTIF('Raw Data'!B3:B179,"W03") -> 16 | D34: =AVERAGEIF('Raw Data'!B3:B179,"W03",'Raw Data'!O3:O179) -> 4.13375 | E34: =SUMIF('Raw Data'!B3:B179,"W03",'Raw Data'!N3:N179) -> 268 | F34: Consistent output
A35: W04 | B35: =SUMIF('Raw Data'!B3:B179,"W04",'Raw Data'!F3:F179) -> 37111 | C35: =COUNTIF('Raw Data'!B3:B179,"W04") -> 13 | D35: =AVERAGEIF('Raw Data'!B3:B179,"W04",'Raw Data'!O3:O179) -> 2.9607692 | E35: =SUMIF('Raw Data'!B3:B179,"W04",'Raw Data'!N3:N179) -> 139 | F35: Promotional push, lower engagement
A36: W05 | B36: =SUMIF('Raw Data'!B3:B179,"W05",'Raw Data'!F3:F179) -> 84045 | C36: =COUNTIF('Raw Data'!B3:B179,"W05") -> 16 | D36: =AVERAGEIF('Raw Data'!B3:B179,"W05",'Raw Data'!O3:O179) -> 3.55125 | E36: =SUMIF('Raw Data'!B3:B179,"W05",'Raw Data'!N3:N179) -> 287 | F36: Valentine's campaign, community surge
A37: W06 | B37: =SUMIF('Raw Data'!B3:B179,"W06",'Raw Data'!F3:F179) -> 43939 | C37: =COUNTIF('Raw Data'!B3:B179,"W06") -> 13 | D37: =AVERAGEIF('Raw Data'!B3:B179,"W06",'Raw Data'!O3:O179) -> 3.3876923 | E37: =SUMIF('Raw Data'!B3:B179,"W06",'Raw Data'!N3:N179) -> 217 | F37: TikTok viral post, outlier week
A38: W07 | B38: =SUMIF('Raw Data'!B3:B179,"W07",'Raw Data'!F3:F179) -> 36555 | C38: =COUNTIF('Raw Data'!B3:B179,"W07") -> 13 | D38: =AVERAGEIF('Raw Data'!B3:B179,"W07",'Raw Data'!O3:O179) -> 3.0269231 | E38: =SUMIF('Raw Data'!B3:B179,"W07",'Raw Data'!N3:N179) -> 138 | F38: Stable, behind the scenes series
A39: W08 | B39: =SUMIF('Raw Data'!B3:B179,"W08",'Raw Data'!F3:F179) -> 32265 | C39: =COUNTIF('Raw Data'!B3:B179,"W08") -> 13 | D39: =AVERAGEIF('Raw Data'!B3:B179,"W08",'Raw Data'!O3:O179) -> 2.6161538 | E39: =SUMIF('Raw Data'!B3:B179,"W08",'Raw Data'!N3:N179) -> 177 | F39: Educational series high saves
A40: W09 | B40: =SUMIF('Raw Data'!B3:B179,"W09",'Raw Data'!F3:F179) -> 39650 | C40: =COUNTIF('Raw Data'!B3:B179,"W09") -> 13 | D40: =AVERAGEIF('Raw Data'!B3:B179,"W09",'Raw Data'!O3:O179) -> 2.6407692 | E40: =SUMIF('Raw Data'!B3:B179,"W09",'Raw Data'!N3:N179) -> 192 | F40: End of quarter, all-platform push
A41: W10 | B41: =SUMIF('Raw Data'!B3:B179,"W10",'Raw Data'!F3:F179) -> 27821 | C41: =COUNTIF('Raw Data'!B3:B179,"W10") -> 11 | D41: =AVERAGEIF('Raw Data'!B3:B179,"W10",'Raw Data'!O3:O179) -> 3.1172727 | E41: =SUMIF('Raw Data'!B3:B179,"W10",'Raw Data'!N3:N179) -> 110 | F41: Final week, follower growth strong
A42: W11 | B42: =SUMIF('Raw Data'!B3:B179,"W11",'Raw Data'!F3:F179) -> 56412 | C42: =COUNTIF('Raw Data'!B3:B179,"W11") -> 15 | D42: =AVERAGEIF('Raw Data'!B3:B179,"W11",'Raw Data'!O3:O179) -> 3.3686667 | E42: =SUMIF('Raw Data'!B3:B179,"W11",'Raw Data'!N3:N179) -> 256 | F42: Easter, cultural content peaks
A43: W12 | B43: =SUMIF('Raw Data'!B3:B179,"W12",'Raw Data'!F3:F179) -> 40512 | C43: =COUNTIF('Raw Data'!B3:B179,"W12") -> 13 | D43: =AVERAGEIF('Raw Data'!B3:B179,"W12",'Raw Data'!O3:O179) -> 2.7392308 | E43: =SUMIF('Raw Data'!B3:B179,"W12",'Raw Data'!N3:N179) -> 118 | F43: Quarter close, summary push
A44: W13 | B44: =SUMIF('Raw Data'!B3:B179,"W13",'Raw Data'!F3:F179) -> 35502 | C44: =COUNTIF('Raw Data'!B3:B179,"W13") -> 10 | D44: =AVERAGEIF('Raw Data'!B3:B179,"W13",'Raw Data'!O3:O179) -> 3.083 | E44: =SUMIF('Raw Data'!B3:B179,"W13",'Raw Data'!N3:N179) -> 133 | F44: Q1 wrap, engagement consolidates
A47: KEY FINDINGS & RECOMMENDATIONS
A48: Finding 1 | B48: UGC / Testimonial content drives highest engagement across ALL platforms, prioritise this format (target: 25% of monthly content mix).
A49: Finding 2 | B49: Promotional posts consistently underperform (avg eng rate below 1%), reduce from current frequency, use only for major campaign moments.
A50: Finding 3 | B50: TikTok delivers highest raw reach and follower growth, increase posting frequency from current level to 5x per week.
A51: Finding 4 | B51: Community & Cultural content performs 2× better on reach than product posts, leverage Kenyan cultural moments (Madaraka, Easter, etc.).
A52: Finding 5 | B52: LinkedIn engagement rate is strong but reach is low, best used for B2B / merchant audience, not mass consumer awareness.
A54: Source: Simulated 90-day dataset based on real Kenyan fintech social media benchmarks (Dash Social Africa 2025, KWETU Marketing Agency 2025).
